Workbook

Sheet Instrukcija
A1: Tēma | B1: Apraksts
A2: Mērķis | B2: Atzīmē KATRU rindu šajās lapās: vai tā ir nodošanas / closeout prasība? Tad `spectakeoff eval` izmērīs, ko programma atrod pareizi, ko kļūdaini un ko palaiž garām.
A3: Kā aizpildīt | B3: Kolonnā F izvēlies Jā vai Nē (vai ? ja tiešām nav skaidrs - tādas rindas netiek vērtētas). Atver PDF norādītajā lapā, ja teksts nav saprotams bez konteksta.
A4: Jā | B4: Teikums vai saraksta punkts uzliek darbuzņēmējam pienākumu NODOT vai IESNIEGT kaut ko nodošanai/closeout: garantija, O&M rokasgrāmatas, izpilddokumentācija (as-built / record drawings), rezerves daļas, papildu materiāli (attic stock), speciālie instrumenti, apmācība, testu atskaites, sertifikāti un atbilstības apliecinājumi, iesniegumu saraksta punkti (piem. UFGS SD-06/07/09/10/11).
A5: Nē | B5: Būvdarbu metodes, materiālu īpašības, juridiski skaidrojumi ('shall not relieve...'), redaktora piezīmes (NOTE:, 'The Engineer shall...'), virsraksti, lapu galvenes, atsauces uz citām sadaļām, uzstādīšana 'saskaņā ar ražotāja instrukcijām'.
A6: Piemērs Jā | B6: Provide two (2) copies of all manufacturers warranties specified for materials.
A7: Piemērs Jā | B7: Operation and Maintenance Manuals; G, [_____] (punkts zem SD-10)
A8: Piemērs Nē | B8: Air-entraining admixtures shall meet the requirements of ASTM C260.
A9: Piemērs Nē | B9: Manufacturer's certifications shall not relieve the Contractor of the responsibility...
A10: Svarīgi | B10: Neskaties, ko atrada programma, pirms neesi atzīmējis pats - citādi mērījums būs neobjektīvs. Ja failā ir kolonna 'Programma atrada', to var paslēpt.
A11: Pēc tam | B11: Saglabā failu un palaid: spectakeoff eval etalons.xlsx (programma pati atkārtoti apstrādās tos pašus PDF un salīdzinās). Lapas, kur kaut viena rinda nav atzīmēta, netiek vērtētas.

Sheet Etalons
A1: ID | B1: Fails | C1: Lapa | D1: Nr. lapā | E1: Teksts (oriģināls) | F1: Prasība? (Jā/Nē) | G1: Piezīme
A2: 150-5370-10H-P0103-001 | B2: 150-5370-10H.pdf | C2: 103 | D2: 1 | E2: 12/21/2018 AC 150/5370-10H | F2: Nē
A3: 150-5370-10H-P0103-002 | B3: 150-5370-10H.pdf | C3: 103 | D3: 2 | E3: b. Removal of Inlets/Manholes. | F3: Nē
A4: 150-5370-10H-P0103-003 | B4: 150-5370-10H.pdf | C4: 103 | D4: 3 | E4: [ Where indicated on the plans or as directed by the RPR, inlets and/or manholes shall be removed and legally disposed of off-site in a timely fashion after removal. | F4: Nē
A5: 150-5370-10H-P0103-004 | B5: 150-5370-10H.pdf | C5: 103 | D5: 4 | E5: Excavations after removal shall be backfilled with material equal or better in quality than adjacent embankment. | F5: Nē
A6: 150-5370-10H-P0103-005 | B6: 150-5370-10H.pdf | C6: 103 | D6: 5 | E6: When under paved areas must be compacted to [ 95% ] of ASTM [ D1557 ] [ D698 ], when outside of paved areas must be compacted to [ 95% ] of ASTM D698. | F6: Nē
A7: 150-5370-10H-P0103-006 | B7: 150-5370-10H.pdf | C7: 103 | D7: 6 | E7: [ Not used. ] ] | F7: Nē
A8: 150-5370-10H-P0103-007 | B8: 150-5370-10H.pdf | C8: 103 | D8: 7 | E8: c. Removal of [ ]. | F8: Nē
A9: 150-5370-10H-P0103-008 | B9: 150-5370-10H.pdf | C9: 103 | D9: 8 | E9: METHOD OF MEASUREMENT | F9: Nē
A10: 150-5370-10H-P0103-009 | B10: 150-5370-10H.pdf | C10: 103 | D10: 9 | E10: [ 101-4.1 Lump sum. | F10: Nē
A11: 150-5370-10H-P0103-010 | B11: 150-5370-10H.pdf | C11: 103 | D11: 10 | E11: No separate measurement for payment will be made. | F11: Nē
A12: 150-5370-10H-P0103-011 | B12: 150-5370-10H.pdf | C12: 103 | D12: 11 | E12: The work covered by this section shall be considered as a subsidiary obligation of the Contractor and covered under the other contract items. ] | F12: Nē
A13: 150-5370-10H-P0103-012 | B13: 150-5370-10H.pdf | C13: 103 | D13: 12 | E13: [ 101-4.1 Pavement removal. | F13: Nē
... A382: 150-5370-10H-P0718-031 | B382: 150-5370-10H.pdf | C382: 718 | D382: 31 | E382: Item L-119 Airport Obstruction Lights 710 | F382: Nē

Sheet Lapas
A1: Fails | B1: Lapa | C1: Rindas | D1: Atzīmētas | E1: Gatava?
A2: 150-5370-10H.pdf | B2: 103 | C2: =COUNTIFS(Etalons!B:B,A2,Etalons!C:C,B2) | D2: =COUNTIFS(Etalons!B:B,A2,Etalons!C:C,B2,Etalons!F:F,"<>") | E2: =IF(D2=C2,"Jā","Nē")
A3: 150-5370-10H.pdf | B3: 141 | C3: =COUNTIFS(Etalons!B:B,A3,Etalons!C:C,B3) | D3: =COUNTIFS(Etalons!B:B,A3,Etalons!C:C,B3,Etalons!F:F,"<>") | E3: =IF(D3=C3,"Jā","Nē")
A4: 150-5370-10H.pdf | B4: 183 | C4: =COUNTIFS(Etalons!B:B,A4,Etalons!C:C,B4) | D4: =COUNTIFS(Etalons!B:B,A4,Etalons!C:C,B4,Etalons!F:F,"<>") | E4: =IF(D4=C4,"Jā","Nē")
A5: 150-5370-10H.pdf | B5: 242 | C5: =COUNTIFS(Etalons!B:B,A5,Etalons!C:C,B5) | D5: =COUNTIFS(Etalons!B:B,A5,Etalons!C:C,B5,Etalons!F:F,"<>") | E5: =IF(D5=C5,"Jā","Nē")
A6: 150-5370-10H.pdf | B6: 310 | C6: =COUNTIFS(Etalons!B:B,A6,Etalons!C:C,B6) | D6: =COUNTIFS(Etalons!B:B,A6,Etalons!C:C,B6,Etalons!F:F,"<>") | E6: =IF(D6=C6,"Jā","Nē")
A7: 150-5370-10H.pdf | B7: 428 | C7: =COUNTIFS(Etalons!B:B,A7,Etalons!C:C,B7) | D7: =COUNTIFS(Etalons!B:B,A7,Etalons!C:C,B7,Etalons!F:F,"<>") | E7: =IF(D7=C7,"Jā","Nē")
A8: 150-5370-10H.pdf | B8: 464 | C8: =COUNTIFS(Etalons!B:B,A8,Etalons!C:C,B8) | D8: =COUNTIFS(Etalons!B:B,A8,Etalons!C:C,B8,Etalons!F:F,"<>") | E8: =IF(D8=C8,"Jā","Nē")
A9: 150-5370-10H.pdf | B9: 540 | C9: =COUNTIFS(Etalons!B:B,A9,Etalons!C:C,B9) | D9: =COUNTIFS(Etalons!B:B,A9,Etalons!C:C,B9,Etalons!F:F,"<>") | E9: =IF(D9=C9,"Jā","Nē")
A10: 150-5370-10H.pdf | B10: 551 | C10: =COUNTIFS(Etalons!B:B,A10,Etalons!C:C,B10) | D10: =COUNTIFS(Etalons!B:B,A10,Etalons!C:C,B10,Etalons!F:F,"<>") | E10: =IF(D10=C10,"Jā","Nē")
A11: 150-5370-10H.pdf | B11: 555 | C11: =COUNTIFS(Etalons!B:B,A11,Etalons!C:C,B11) | D11: =COUNTIFS(Etalons!B:B,A11,Etalons!C:C,B11,Etalons!F:F,"<>") | E11: =IF(D11=C11,"Jā","Nē")
A12: 150-5370-10H.pdf | B12: 575 | C12: =COUNTIFS(Etalons!B:B,A12,Etalons!C:C,B12) | D12: =COUNTIFS(Etalons!B:B,A12,Etalons!C:C,B12,Etalons!F:F,"<>") | E12: =IF(D12=C12,"Jā","Nē")
A13: 150-5370-10H.pdf | B13: 590 | C13: =COUNTIFS(Etalons!B:B,A13,Etalons!C:C,B13) | D13: =COUNTIFS(Etalons!B:B,A13,Etalons!C:C,B13,Etalons!F:F,"<>") | E13: =IF(D13=C13,"Jā","Nē")
... A16: 150-5370-10H.pdf | B16: 718 | C16: =COUNTIFS(Etalons!B:B,A16,Etalons!C:C,B16) | D16: =COUNTIFS(Etalons!B:B,A16,Etalons!C:C,B16,Etalons!F:F,"<>") | E16: =IF(D16=C16,"Jā","Nē")

Sheet _meta
A1: {"tool_version": "4.0.0", "seed": 1, "sample": 20, "pages_spec": "103,141,183,242,310,428,464,540,551,555,575,590,618,700,718", "show_predictions": false, "sources": [{"name": "150-5370-10H.pdf", "path": "/tmp/claude-0/-home-user-workflows-starter-template/02873300-0aa4-5b5a-a8bb-9cae7051367b/scratchpad/holdout2/150-5370-10H.pdf", "sha256": "5b573a0979564a49bc052c2c84cc774218155b691e4511722aeb42969bededef"}], "pages": [{"source": "150-5370-10H.pdf", "page": 103}, {"source": "150-5370-10H.pdf", "page": 141}, {"source": "150-5370-10H.pdf", "page": 183}, {"source": "150-5370-10H.pdf", "page": 242}, {"source": "150-5370-10H.pdf", "page": 310}, {"source": "150-5370-10H.pdf", "page": 428}, {"source": "150-5370-10H.pdf", "page": 464}, {"source": "150-5370-10H.pdf", "page": 540}, {"source": "150-5370-10H.pdf", "page": 551}, {"source": "150-5370-10H.pdf", "page": 555}, {"source": "150-5370-10H.pdf", "page": 575}, {"source": "150-5370-10H.pdf", "page": 590}, {"source": "150-5370-10H.pdf", "page": 618}, {"source": "150-5370-10H.pdf", "page": 700}, {"source": "150-5370-10H.pdf", "page": 718}]}
